mcp_search/__init__.py
mcp_search/__main__.py
mcp_search/server.py
mcp_gemini_search-0.2.6.dist-info/METADATA
mcp_gemini_search-0.2.6.dist-info/WHEEL
mcp_gemini_search-0.2.6.dist-info/entry_points.txt
mcp_gemini_search-0.2.6.dist-info/licenses/LICENSE
mcp_gemini_search-0.2.6.dist-info/RECORD
