Metadata-Version: 2.4
Name: mcp-gemini-search
Version: 0.2.6
Summary: MCP Server for web search via Gemini's grounding API
Project-URL: Homepage, https://github.com/cubase/mcp-search-server
Project-URL: Repository, https://github.com/cubase/mcp-search-server
Author: cubase
License-Expression: MIT
License-File: LICENSE
Keywords: ai,anthropic,claude,gemini,llm,mcp,search
Classifier: Development Status :: 4 - Beta
Classifier: Intended Audience :: Developers
Classifier: License :: OSI Approved :: MIT License
Classifier: Programming Language :: Python :: 3
Classifier: Programming Language :: Python :: 3.10
Classifier: Programming Language :: Python :: 3.11
Classifier: Programming Language :: Python :: 3.12
Classifier: Programming Language :: Python :: 3.13
Classifier: Topic :: Scientific/Engineering :: Artificial Intelligence
Requires-Python: >=3.10
Requires-Dist: httpx>=0.25.0
Requires-Dist: mcp>=1.0.0
